register/__init__.py
register/exceptions.py
register/models.py
register/repository.py
register/use_cases.py
register/tests/__init__.py
register/tests/input.py
register/tests/test_customer.py
register/tests/test_home_address.py
register/tests/test_office_address.py
register/tests/test_register_customer.py
util/__init__.py
util/address.py
util/collection.py
util/constants.py
util/datetime.py
util/exceptions.py
util/password.py
util/string.py
preeti_bhojan_core_rahem027-0.0.1.dist-info/LICENSE
preeti_bhojan_core_rahem027-0.0.1.dist-info/METADATA
preeti_bhojan_core_rahem027-0.0.1.dist-info/WHEEL
preeti_bhojan_core_rahem027-0.0.1.dist-info/top_level.txt
preeti_bhojan_core_rahem027-0.0.1.dist-info/RECORD
